{
    "columns": [
      { "title": "Event Name", "field": "name" },
      { "title": "Approriate Response", "field": "response" },
      { "title": "Data to be considered", "field": "data" },
      { "title": "Point of Contact", "field": "contact" },
      {
        "title": "Anomaly Expected/Actual",
        "field": "anomaly",
        "lookup": { "34": "Higher", "63": "Lower", "90": "Unknown Observations" }
      },
      { "title": "Cluster", "field": "cluster" }
    ],
    "data": [
      { "name": "Radar Power Loss", "response": "Reset Sensor, Contact Listed Point Of Contact, Replace Sensor Feed with replacement sensor data", "data": "Observations Time Series", "contact": "John Smith","anomaly": 63 },
      { "name": "Sensor Alignment Drift", "response": "Recalibrate Sensor, Follow Instructions 14.2.1", "data": "Average Sat Altitude, Average Sat Data, Average Sat Detection Rate", "contact": "Chase Morgan","anomaly": 90 },
      { "name": "Low Correlation With Catalog", "response": "Immediatly Escalate to Listed Point of Contact", "data": "Known Object Catalog, Detected Object Database", "contact": "John Smith","anomaly": 90 },
      { "name": "Un-cataloged object detected", "response": "Determine root cause. Generate additional tasking", "data": "Rate of new object detection,correlation with other un-cataloged objects detected", "contact": "Larry Anderson","anomaly": 34 },
      { "name": "Missed observation", "response": "Determine root cause, expected", "data": "Rate of missed passes", "contact": "Bob Williams","anomaly": 63 }
    ]
  }